odoo/addons/account_invoice_mass_sending/README.rst
odoo/addons/account_invoice_mass_sending/__init__.py
odoo/addons/account_invoice_mass_sending/__manifest__.py
odoo/addons/account_invoice_mass_sending/i18n/account_invoice_mass_sending.pot
odoo/addons/account_invoice_mass_sending/i18n/es.po
odoo/addons/account_invoice_mass_sending/i18n/fr.po
odoo/addons/account_invoice_mass_sending/models/__init__.py
odoo/addons/account_invoice_mass_sending/models/account_invoice.py
odoo/addons/account_invoice_mass_sending/readme/CONFIGURE.rst
odoo/addons/account_invoice_mass_sending/readme/CONTRIBUTORS.rst
odoo/addons/account_invoice_mass_sending/readme/DESCRIPTION.rst
odoo/addons/account_invoice_mass_sending/readme/USAGE.rst
odoo/addons/account_invoice_mass_sending/static/description/icon.png
odoo/addons/account_invoice_mass_sending/static/description/index.html
odoo/addons/account_invoice_mass_sending/views/account_invoice_views.xml
odoo12_addon_account_invoice_mass_sending-12.0.1.0.0.99.dev8.dist-info/METADATA
odoo12_addon_account_invoice_mass_sending-12.0.1.0.0.99.dev8.dist-info/WHEEL
odoo12_addon_account_invoice_mass_sending-12.0.1.0.0.99.dev8.dist-info/top_level.txt
odoo12_addon_account_invoice_mass_sending-12.0.1.0.0.99.dev8.dist-info/RECORD
